{"entity": [{"left": 1, "right": 3, "name": "\u5c0f\u65f6", "CUI": "C0439227"}, {"left": 7, "right": 9, "name": "\u82f9\u679c", "CUI": "C0003625"}, {"left": 12, "right": 14, "name": "\u8179\u90e8", "CUI": "C0000726"}, {"left": 14, "right": 16, "name": "\u75bc\u75db", "CUI": "C0030193"}, {"left": 18, "right": 20, "name": "\u6076\u5fc3", "CUI": "C0027497"}, {"left": 22, "right": 24, "name": "\u5455\u5410", "CUI": "C0016927"}, {"left": 26, "right": 28, "name": "\u6392\u4fbf", "CUI": "C0011135"}, {"left": 28, "right": 30, "name": "\u6392\u6c14", "CUI": "C0016204"}, {"left": 30, "right": 32, "name": "\u6b63\u5e38", "CUI": "C0205307"}, {"left": 34, "right": 36, "name": "\u53d1\u70ed", "CUI": "C0015967"}, {"left": 36, "right": 38, "name": "\u76d7\u6c57", "CUI": "C0028081"}, {"left": 43, "right": 45, "name": "\u957f\u671f", "CUI": "C0439590"}, {"left": 45, "right": 47, "name": "\u80c3\u90e8", "CUI": "C1268119"}, {"left": 47, "right": 49, "name": "\u4e0d\u9002", "CUI": "C0231218"}, {"left": 57, "right": 59, "name": "\u5177\u4f53", "CUI": "C0205369"}, {"left": 62, "right": 64, "name": "\u5426\u8ba4", "CUI": "C0332319"}, {"left": 64, "right": 68, "name": "\u836f\u7269\u8fc7\u654f\u53f2", "CUI": "C0455589"}, {"left": 66, "right": 68, "name": "\u8fc7\u654f", "CUI": "C0002111"}, {"left": 69, "right": 71, "name": "\u8179\u75db", "CUI": "C0000737"}, {"left": 74, "right": 76, "name": "\u809d\u80be", "CUI": "C1268355"}, {"left": 83, "right": 85, "name": "\u5e38\u89c4", "CUI": "C0205547"}, {"left": 293, "right": 295, "name": "\u4f53\u6e29", "CUI": "C0005903"}, {"left": 302, "right": 304, "name": "\u8109\u640f", "CUI": "C0183426"}, {"left": 311, "right": 313, "name": "\u547c\u5438", "CUI": "C0004048"}, {"left": 320, "right": 322, "name": "\u6536\u7f29", "CUI": "C1261287"}, {"left": 331, "right": 333, "name": "\u8212\u5f20", "CUI": "C0012000"}, {"left": 351, "right": 353, "name": "\u60c5\u51b5", "CUI": "C0868928"}, {"left": 355, "right": 357, "name": "\u6b65\u884c", "CUI": "C0080331"}, {"left": 364, "right": 366, "name": "\u53cc\u80ba", "CUI": "C0225754"}, {"left": 374, "right": 376, "name": "\u660e\u663e", "CUI": "C0522501"}, {"left": 388, "right": 393, "name": "\u53f3\u4e0b\u8179\u75bc\u75db", "CUI": "C0694551"}, {"left": 389, "right": 393, "name": "\u4e0b\u8179\u90e8\u538b\u75db", "CUI": "C0578099"}, {"left": 390, "right": 392, "name": "\u8179\u538b", "CUI": "C0429218"}, {"left": 391, "right": 393, "name": "\u538b\u75db", "CUI": "C0234233"}], "note": "6\u5c0f\u65f6\u524d\u60a3\u8005\u5403\u82f9\u679c\u540e\u51fa\u73b0\u8179\u90e8\u75bc\u75db\uff0c\u4f34\u6076\u5fc3\uff0c\u65e0\u5455\u5410\uff0c\u6709\u6392\u4fbf\u6392\u6c14\u6b63\u5e38\uff0c\u65e0\u53d1\u70ed\u76d7\u6c57\u3002\u65e2\u5f80\u53f2\uff1a\u957f\u671f\u80c3\u90e8\u4e0d\u9002\uff0c\u670d\u7528\u4e2d\u836f\u8c03\u7406\uff0c\u5177\u4f53\u4e0d\u8be6\u3002\u5426\u8ba4\u836f\u7269\u8fc7\u654f\u3002\u8179\u75db6\u5c0f\u65f6\u809d\u80be\u529f\u5927\u81f4\u6b63\u5e38\uff0c\u8840\u5e38\u89c4\uff1a CRP(B) <1 mg/L, WBC 11.18 \u2191(High) 10^9/L, RBC 4.52 10^12/L, HGB 117.00 g/L, NEUT# 9.02 \u2191(High) 10^9/L, LY# 1.40 10^9/L, MONO# 0.67 \u2191(High) 10^9/L, EOS# 0.03 10^9/L, BASO# 0.06 10^9/L, NEUT% 80.70 \u2191(High) %\uff1b\u4f53\u6e29\uff1a36.5\u2103\uff1b\u8109\u640f\uff1a77\u6b21/\u5206\uff1b\u547c\u5438\uff1a18\u6b21/\u5206\uff1b\u6536\u7f29\u538b\uff1a94mmHg\uff1b\u8212\u5f20\u538b\uff1a57mmHg\uff1b\u8840\u6c27\uff1a98%\u3002\u4e00\u822c\u60c5\u51b5\u53ef\uff0c\u6b65\u884c\u5165\u5ba4\uff0c\u54bd\u4e0d\u7ea2\uff0c\u53cc\u80ba\u547c\u5438\u97f3\u6e05\uff0c\u672a\u95fb\u53ca\u660e\u663e\u5e72\u6e7f\u7f57\u97f3\uff0c\u5fc3\u5f8b\u9f50\uff0c\u8179\u8f6f\uff0c\u53f3\u4e0b\u8179\u538b\u75db\uff0c\u65e0\u53cd\u8df3\u75db\u53ca\u808c\u7d27\u5f20\uff0c\u53cc\u4e0b\u80a2\u65e0\u6c34\u80bf\u3002", "label": [3, 14]}